{ "PaddlePositionX" : 684, "PaddlePositionY" : 686, "BallPositionX" : 729, "BallPositionY" : 292, "Username" : "first", "ChancePoints" : 3, "Score" : 950, "ChanceGivingAbility" : 5, "PaddleExpansionAbility" : 5, "UnstoppableAbility" : 5, "RocketAbility" : 5, "Ymirfreq" : 0, "YmirProb1" : 5.0, "YmirProb2" : 5.0, "YmirProb3" : 5.0, "ObjectList" : [["Obstacle{pos=PosVector{x=497, y=278}, typeVariable=WallMaria", "PosVector{x=311, y=278}", "false", "ealth 1", "vmoving0", "Qeft-1<", "righT-1>"], ["Obstacle{pos=PosVector{x=735, y=359}, typeVariable=PandorasBox", "PosVector{x=459, y=359}", "false", "ealth 1", "vmoving0", "Qeft-1<", "righT-1>"], ["Obstacle{pos=PosVector{x=1050, y=380}, typeVariable=WallMaria", "PosVector{x=655, y=380}", "false", "ealth 1", "vmoving0", "Qeft-1<", "righT-1>"], ["Obstacle{pos=PosVector{x=1276, y=335}, typeVariable=GiftOfUranus", "PosVector{x=796, y=335}", "false", "ealth 1", "vmoving0", "Qeft-1<", "righT-1>"], ["Obstacle{pos=PosVector{x=1141, y=301}, typeVariable=WallMaria", "PosVector{x=712, y=301}", "false", "ealth 1", "vmoving0", "Qeft-1<", "righT-1>"], ["Obstacle{pos=PosVector{x=875, y=312}, typeVariable=GiftOfUranus", "PosVector{x=546, y=312}", "false", "ealth 1", "vmoving0", "Qeft-1<", "righT-1>"], ["Obstacle{pos=PosVector{x=1204, y=296}, typeVariable=WallMaria", "PosVector{x=751, y=296}", "false", "ealth 1", "vmoving0", "Qeft-1<", "righT-1>"], ["Obstacle{pos=PosVector{x=790, y=147}, typeVariable=WallMaria", "PosVector{x=493, y=147}", "false", "ealth 1", "vmoving0", "Qeft-1<", "righT-1>"], ["Obstacle{pos=PosVector{x=1090, y=250}, typeVariable=PandorasBox", "PosVector{x=680, y=250}", "false", "ealth 1", "vmoving0", "Qeft-1<", "righT-1>"], ["Obstacle{pos=PosVector{x=639, y=343}, typeVariable=WallMaria", "PosVector{x=374, y=343}", "false", "ealth 1", "vmoving1", "Qeft561<", "righT699>"], ["Obstacle{pos=PosVector{x=639, y=411}, typeVariable=GiftOfUranus", "PosVector{x=399, y=411}", "false", "ealth 1", "vmoving0", "Qeft-1<", "righT-1>"], ["Obstacle{pos=PosVector{x=1189, y=104}, typeVariable=GiftOfUranus", "PosVector{x=742, y=104}", "false", "ealth 1", "vmoving0", "Qeft-1<", "righT-1>"], ["Obstacle{pos=PosVector{x=946, y=314}, typeVariable=WallMaria", "PosVector{x=590, y=314}", "false", "ealth 1", "vmoving0", "Qeft-1<", "righT-1>"], ["Obstacle{pos=PosVector{x=463, y=207}, typeVariable=WallMaria", "PosVector{x=289, y=207}", "false", "ealth 1", "vmoving0", "Qeft-1<", "righT-1>"], ["Obstacle{pos=PosVector{x=457, y=302}, typeVariable=SteinsGate", "PosVector{x=285, y=302}", "false", "ealth 3", "vmoving0", "Qeft-1<", "righT-1>"], ["Obstacle{pos=PosVector{x=591, y=257}, typeVariable=WallMaria", "PosVector{x=369, y=257}", "false", "ealth 1", "vmoving0", "Qeft-1<", "righT-1>"], ["Obstacle{pos=PosVector{x=1037, y=204}, typeVariable=WallMaria", "PosVector{x=647, y=204}", "false", "ealth 1", "vmoving0", "Qeft-1<", "righT-1>"], ["Obstacle{pos=PosVector{x=784, y=312}, typeVariable=WallMaria", "PosVector{x=489, y=312}", "false", "ealth 1", "vmoving0", "Qeft-1<", "righT-1>"], ["Obstacle{pos=PosVector{x=249, y=192}, typeVariable=WallMaria", "PosVector{x=156, y=192}", "false", "ealth 1", "vmoving0", "Qeft-1<", "righT-1>"], ["Obstacle{pos=PosVector{x=1096, y=200}, typeVariable=WallMaria", "PosVector{x=684, y=200}", "false", "ealth 1", "vmoving0", "Qeft-1<", "righT-1>"], ["Obstacle{pos=PosVector{x=1281, y=70}, typeVariable=SteinsGate", "PosVector{x=799, y=70}", "false", "ealth 1", "vmoving0", "Qeft-1<", "righT-1>"], ["Obstacle{pos=PosVector{x=20, y=379}, typeVariable=WallMaria", "PosVector{x=13, y=379}", "false", "ealth 1", "vmoving0", "Qeft-1<", "righT-1>"], ["Obstacle{pos=PosVector{x=81, y=378}, typeVariable=WallMaria", "PosVector{x=51, y=378}", "false", "ealth 1", "vmoving0", "Qeft-1<", "righT-1>"], ["Obstacle{pos=PosVector{x=339, y=210}, typeVariable=PandorasBox", "PosVector{x=212, y=210}", "false", "ealth 1", "vmoving0", "Qeft-1<", "righT-1>"], ["Obstacle{pos=PosVector{x=297, y=128}, typeVariable=WallMaria", "PosVector{x=186, y=128}", "false", "ealth 1", "vmoving0", "Qeft289<", "righT312>"], ["Obstacle{pos=PosVector{x=333, y=268}, typeVariable=WallMaria", "PosVector{x=208, y=268}", "false", "ealth 1", "vmoving0", "Qeft-1<", "righT-1>"], ["Obstacle{pos=PosVector{x=958, y=354}, typeVariable=WallMaria", "PosVector{x=598, y=354}", "false", "ealth 1", "vmoving0", "Qeft-1<", "righT-1>"], ["Obstacle{pos=PosVector{x=886, y=290}, typeVariable=SteinsGate", "PosVector{x=553, y=290}", "false", "ealth 3", "vmoving0", "Qeft-1<", "righT-1>"], ["Obstacle{pos=PosVector{x=1018, y=348}, typeVariable=SteinsGate", "PosVector{x=635, y=348}", "false", "ealth 3", "vmoving0", "Qeft-1<", "righT-1>"], ["Obstacle{pos=PosVector{x=938, y=145}, typeVariable=GiftOfUranus", "PosVector{x=585, y=145}", "false", "ealth 1", "vmoving0", "Qeft-1<", "righT-1>"], ["Obstacle{pos=PosVector{x=81, y=343}, typeVariable=WallMaria", "PosVector{x=76, y=343}", "false", "ealth 1", "vmoving1", "Qeft73<", "righT158>"], ["Obstacle{pos=PosVector{x=146, y=265}, typeVariable=WallMaria", "PosVector{x=129, y=265}", "false", "ealth 1", "vmoving1", "Qeft106<", "righT221>"], ["Obstacle{pos=PosVector{x=264, y=381}, typeVariable=SteinsGate", "PosVector{x=165, y=381}", "false", "ealth 3", "vmoving0", "Qeft-1<", "righT-1>"], ["Obstacle{pos=PosVector{x=1027, y=247}, typeVariable=WallMaria", "PosVector{x=641, y=247}", "false", "ealth 1", "vmoving0", "Qeft-1<", "righT-1>"], ["Obstacle{pos=PosVector{x=64, y=82}, typeVariable=WallMaria", "PosVector{x=41, y=82}", "false", "ealth 1", "vmoving0", "Qeft-1<", "righT-1>"], ["Obstacle{pos=PosVector{x=577, y=199}, typeVariable=PandorasBox", "PosVector{x=360, y=199}", "false", "ealth 1", "vmoving0", "Qeft-1<", "righT-1>"], ["Obstacle{pos=PosVector{x=702, y=316}, typeVariable=WallMaria", "PosVector{x=432, y=316}", "false", "ealth 1", "vmoving1", "Qeft592<", "righT745>"], ["Obstacle{pos=PosVector{x=344, y=188}, typeVariable=WallMaria", "PosVector{x=215, y=188}", "false", "ealth 1", "vmoving0", "Qeft-1<", "righT-1>"], ["Obstacle{pos=PosVector{x=142, y=377}, typeVariable=WallMaria", "PosVector{x=127, y=377}", "false", "ealth 1", "vmoving1", "Qeft134<", "righT225>"], ["Obstacle{pos=PosVector{x=54, y=204}, typeVariable=SteinsGate", "PosVector{x=34, y=204}", "false", "ealth 2", "vmoving0", "Qeft-1<", "righT-1>"], ["Obstacle{pos=PosVector{x=260, y=264}, typeVariable=WallMaria", "PosVector{x=163, y=264}", "false", "ealth 1", "vmoving0", "Qeft257<", "righT295>"], ["Obstacle{pos=PosVector{x=447, y=263}, typeVariable=WallMaria", "PosVector{x=279, y=263}", "false", "ealth 1", "vmoving0", "Qeft-1<", "righT-1>"], ["Obstacle{pos=PosVector{x=373, y=74}, typeVariable=WallMaria", "PosVector{x=233, y=74}", "false", "ealth 1", "vmoving0", "Qeft-1<", "righT-1>"], ["Obstacle{pos=PosVector{x=1212, y=147}, typeVariable=WallMaria", "PosVector{x=756, y=147}", "false", "ealth 1", "vmoving0", "Qeft-1<", "righT-1>"], ["Obstacle{pos=PosVector{x=472, y=119}, typeVariable=PandorasBox", "PosVector{x=295, y=119}", "false", "ealth 1", "vmoving0", "Qeft-1<", "righT-1>"], ["Obstacle{pos=PosVector{x=889, y=84}, typeVariable=WallMaria", "PosVector{x=604, y=84}", "false", "ealth 1", "vmoving1", "Qeft869<", "righT1069>"], ["Obstacle{pos=PosVector{x=734, y=339}, typeVariable=PandorasBox", "PosVector{x=458, y=339}", "false", "ealth 1", "vmoving0", "Qeft-1<", "righT-1>"], ["Obstacle{pos=PosVector{x=1284, y=236}, typeVariable=WallMaria", "PosVector{x=801, y=236}", "false", "ealth 1", "vmoving0", "Qeft-1<", "righT-1>"], ["Obstacle{pos=PosVector{x=614, y=286}, typeVariable=WallMaria", "PosVector{x=383, y=286}", "false", "ealth 1", "vmoving0", "Qeft-1<", "righT-1>"], ["Obstacle{pos=PosVector{x=15, y=133}, typeVariable=WallMaria", "PosVector{x=10, y=133}", "false", "ealth 1", "vmoving0", "Qeft-1<", "righT-1>"], ["Obstacle{pos=PosVector{x=307, y=102}, typeVariable=WallMaria", "PosVector{x=192, y=102}", "false", "ealth 1", "vmoving0", "Qeft289<", "righT312>"], ["Obstacle{pos=PosVector{x=344, y=332}, typeVariable=WallMaria", "PosVector{x=215, y=332}", "false", "ealth 1", "vmoving0", "Qeft-1<", "righT-1>"], ["Obstacle{pos=PosVector{x=1147, y=191}, typeVariable=WallMaria", "PosVector{x=716, y=191}", "false", "ealth 1", "vmoving0", "Qeft-1<", "righT-1>"], ["Obstacle{pos=PosVector{x=321, y=241}, typeVariable=WallMaria", "PosVector{x=225, y=241}", "false", "ealth 1", "vmoving1", "Qeft261<", "righT380>"], ["Obstacle{pos=PosVector{x=795, y=346}, typeVariable=WallMaria", "PosVector{x=496, y=346}", "false", "ealth 1", "vmoving0", "Qeft-1<", "righT-1>"], ["Obstacle{pos=PosVector{x=880, y=339}, typeVariable=WallMaria", "PosVector{x=549, y=339}", "false", "ealth 1", "vmoving0", "Qeft-1<", "righT-1>"], ["Obstacle{pos=PosVector{x=1069, y=177}, typeVariable=WallMaria", "PosVector{x=667, y=177}", "false", "ealth 1", "vmoving0", "Qeft-1<", "righT-1>"], ["Obstacle{pos=PosVector{x=812, y=167}, typeVariable=WallMaria", "PosVector{x=469, y=167}", "false", "ealth 1", "vmoving1", "Qeft752<", "righT813>"], ["Obstacle{pos=PosVector{x=325, y=297}, typeVariable=WallMaria", "PosVector{x=203, y=297}", "false", "ealth 1", "vmoving0", "Qeft-1<", "righT-1>"], ["Obstacle{pos=PosVector{x=1283, y=380}, typeVariable=WallMaria", "PosVector{x=800, y=380}", "false", "ealth 1", "vmoving0", "Qeft-1<", "righT-1>"], ["Obstacle{pos=PosVector{x=21, y=359}, typeVariable=WallMaria", "PosVector{x=14, y=359}", "false", "ealth 1", "vmoving0", "Qeft0<", "righT42>"], ["Obstacle{pos=PosVector{x=415, y=127}, typeVariable=WallMaria", "PosVector{x=259, y=127}", "false", "ealth 1", "vmoving0", "Qeft-1<", "righT-1>"], ["Obstacle{pos=PosVector{x=554, y=136}, typeVariable=WallMaria", "PosVector{x=346, y=136}", "false", "ealth 1", "vmoving0", "Qeft-1<", "righT-1>"], ["Obstacle{pos=PosVector{x=704, y=149}, typeVariable=WallMaria", "PosVector{x=439, y=149}", "false", "ealth 1", "vmoving0", "Qeft-1<", "righT-1>"], ["Obstacle{pos=PosVector{x=1199, y=168}, typeVariable=WallMaria", "PosVector{x=748, y=168}", "false", "ealth 1", "vmoving0", "Qeft-1<", "righT-1>"], ["Obstacle{pos=PosVector{x=236, y=110}, typeVariable=WallMaria", "PosVector{x=148, y=110}", "false", "ealth 1", "vmoving1", "Qeft183<", "righT259>"], ["Obstacle{pos=PosVector{x=1278, y=197}, typeVariable=WallMaria", "PosVector{x=797, y=197}", "false", "ealth 1", "vmoving0", "Qeft-1<", "righT-1>"], ["Obstacle{pos=PosVector{x=539, y=404}, typeVariable=WallMaria", "PosVector{x=337, y=404}", "false", "ealth 1", "vmoving0", "Qeft-1<", "righT-1>"], ["Obstacle{pos=PosVector{x=767, y=191}, typeVariable=WallMaria", "PosVector{x=479, y=191}", "false", "ealth 1", "vmoving0", "Qeft-1<", "righT-1>"], ["Obstacle{pos=PosVector{x=1270, y=118}, typeVariable=WallMaria", "PosVector{x=792, y=118}", "false", "ealth 1", "vmoving0", "Qeft-1<", "righT-1>"], ["Obstacle{pos=PosVector{x=13, y=329}, typeVariable=WallMaria", "PosVector{x=3, y=329}", "false", "ealth 1", "vmoving1", "Qeft0<", "righT82>"], ["Obstacle{pos=PosVector{x=874, y=398}, typeVariable=WallMaria", "PosVector{x=545, y=398}", "false", "ealth 1", "vmoving0", "Qeft-1<", "righT-1>"], ["Obstacle{pos=PosVector{x=430, y=348}, typeVariable=WallMaria", "PosVector{x=269, y=348}", "false", "ealth 1", "vmoving1", "Qeft397<", "righT471>"], ["Obstacle{pos=PosVector{x=392, y=311}, typeVariable=WallMaria", "PosVector{x=245, y=311}", "false", "ealth 1", "vmoving0", "Qeft-1<", "righT-1>"], ["Obstacle{pos=PosVector{x=790, y=283}, typeVariable=WallMaria", "PosVector{x=493, y=283}", "false", "ealth 1", "vmoving0", "Qeft-1<", "righT-1>"], ["Obstacle{pos=PosVector{x=851, y=173}, typeVariable=GiftOfUranus", "PosVector{x=531, y=173}", "false", "ealth 1", "vmoving0", "Qeft-1<", "righT-1>"], ["Obstacle{pos=PosVector{x=1067, y=135}, typeVariable=GiftOfUranus", "PosVector{x=666, y=135}", "false", "ealth 1", "vmoving0", "Qeft-1<", "righT-1>"], ["Obstacle{pos=PosVector{x=1223, y=375}, typeVariable=WallMaria", "PosVector{x=763, y=375}", "false", "ealth 1", "vmoving0", "Qeft-1<", "righT-1>"], ["Obstacle{pos=PosVector{x=296, y=169}, typeVariable=WallMaria", "PosVector{x=185, y=169}", "false", "ealth 1", "vmoving0", "Qeft-1<", "righT-1>"], ["Obstacle{pos=PosVector{x=851, y=367}, typeVariable=SteinsGate", "PosVector{x=531, y=367}", "false", "ealth 3", "vmoving0", "Qeft-1<", "righT-1>"], ["Obstacle{pos=PosVector{x=158, y=233}, typeVariable=PandorasBox", "PosVector{x=99, y=233}", "false", "ealth 1", "vmoving0", "Qeft-1<", "righT-1>"], ["Obstacle{pos=PosVector{x=843, y=225}, typeVariable=PandorasBox", "PosVector{x=526, y=225}", "false", "ealth 1", "vmoving0", "Qeft-1<", "righT-1>"], ["Obstacle{pos=PosVector{x=350, y=118}, typeVariable=GiftOfUranus", "PosVector{x=219, y=118}", "false", "ealth 1", "vmoving0", "Qeft-1<", "righT-1>"], ["Obstacle{pos=PosVector{x=440, y=84}, typeVariable=WallMaria", "PosVector{x=275, y=84}", "false", "ealth 1", "vmoving0", "Qeft-1<", "righT-1>"], ["Obstacle{pos=PosVector{x=245, y=161}, typeVariable=WallMaria", "PosVector{x=141, y=161}", "false", "ealth 1", "vmoving1", "Qeft125<", "righT258>"], ["Obstacle{pos=PosVector{x=872, y=146}, typeVariable=WallMaria", "PosVector{x=544, y=146}", "false", "ealth 1", "vmoving0", "Qeft-1<", "righT-1>"], ["Obstacle{pos=PosVector{x=369, y=394}, typeVariable=WallMaria", "PosVector{x=231, y=394}", "false", "ealth 1", "vmoving0", "Qeft-1<", "righT-1>"], ["Obstacle{pos=PosVector{x=146, y=295}, typeVariable=WallMaria", "PosVector{x=92, y=295}", "false", "ealth 1", "vmoving0", "Qeft-1<", "righT-1>"], ["Obstacle{pos=PosVector{x=1023, y=328}, typeVariable=WallMaria", "PosVector{x=638, y=328}", "false", "ealth 1", "vmoving0", "Qeft-1<", "righT-1>"], ["Obstacle{pos=PosVector{x=419, y=226}, typeVariable=WallMaria", "PosVector{x=262, y=226}", "false", "ealth 1", "vmoving0", "Qeft411<", "righT424>"], ["Obstacle{pos=PosVector{x=347, y=150}, typeVariable=WallMaria", "PosVector{x=217, y=150}", "false", "ealth 1", "vmoving0", "Qeft-1<", "righT-1>"], ["Obstacle{pos=PosVector{x=519, y=193}, typeVariable=GiftOfUranus", "PosVector{x=324, y=193}", "false", "ealth 1", "vmoving0", "Qeft-1<", "righT-1>"], ["Obstacle{pos=PosVector{x=487, y=96}, typeVariable=WallMaria", "PosVector{x=304, y=96}", "false", "ealth 1", "vmoving0", "Qeft-1<", "righT-1>"], ["Obstacle{pos=PosVector{x=78, y=122}, typeVariable=WallMaria", "PosVector{x=49, y=122}", "false", "ealth 1", "vmoving0", "Qeft-1<", "righT-1>"], ["Obstacle{pos=PosVector{x=583, y=86}, typeVariable=PandorasBox", "PosVector{x=364, y=86}", "false", "ealth 1", "vmoving0", "Qeft-1<", "righT-1>"], ["Obstacle{pos=PosVector{x=924, y=265}, typeVariable=WallMaria", "PosVector{x=577, y=265}", "false", "ealth 1", "vmoving0", "Qeft-1<", "righT-1>"], ["Obstacle{pos=PosVector{x=240, y=302}, typeVariable=WallMaria", "PosVector{x=150, y=302}", "false", "ealth 1", "vmoving0", "Qeft-1<", "righT-1>"], ["Obstacle{pos=PosVector{x=133, y=96}, typeVariable=WallMaria", "PosVector{x=83, y=96}", "false", "ealth 1", "vmoving0", "Qeft-1<", "righT-1>"], ["Obstacle{pos=PosVector{x=196, y=351}, typeVariable=WallMaria", "PosVector{x=123, y=351}", "false", "ealth 1", "vmoving0", "Qeft-1<", "righT-1>"], ["Obstacle{pos=PosVector{x=268, y=76}, typeVariable=WallMaria", "PosVector{x=168, y=76}", "false", "ealth 1", "vmoving0", "Qeft-1<", "righT-1>"], ["Obstacle{pos=PosVector{x=1134, y=136}, typeVariable=WallMaria", "PosVector{x=708, y=136}", "false", "ealth 1", "vmoving1", "Qeft1116<", "righT1173>"], ["Obstacle{pos=PosVector{x=610, y=144}, typeVariable=WallMaria", "PosVector{x=381, y=144}", "false", "ealth 1", "vmoving0", "Qeft-1<", "righT-1>"], ["Obstacle{pos=PosVector{x=509, y=351}, typeVariable=WallMaria", "PosVector{x=318, y=351}", "false", "ealth 1", "vmoving0", "Qeft-1<", "righT-1>"], ["Obstacle{pos=PosVector{x=1266, y=91}, typeVariable=WallMaria", "PosVector{x=790, y=91}", "false", "ealth 1", "vmoving0", "Qeft-1<", "righT-1>"], ["Obstacle{pos=PosVector{x=193, y=192}, typeVariable=SteinsGate", "PosVector{x=121, y=192}", "false", "ealth 3", "vmoving0", "Qeft-1<", "righT-1>"], ["Obstacle{pos=PosVector{x=1131, y=228}, typeVariable=PandorasBox", "PosVector{x=705, y=228}", "false", "ealth 1", "vmoving0", "Qeft-1<", "righT-1>"], ["Obstacle{pos=PosVector{x=628, y=87}, typeVariable=SteinsGate", "PosVector{x=442, y=87}", "false", "ealth 4", "vmoving1", "Qeft608<", "righT808>"]] }